neera_yahlium_clockangle/__init__.py
neera_yahlium_clockangle/angle_calculator.py
neera_yahlium_clockangle-1.0.0.dist-info/LICENSE
neera_yahlium_clockangle-1.0.0.dist-info/METADATA
neera_yahlium_clockangle-1.0.0.dist-info/WHEEL
neera_yahlium_clockangle-1.0.0.dist-info/top_level.txt
neera_yahlium_clockangle-1.0.0.dist-info/RECORD
