Metadata-Version: 2.1
Name: neera-yahlium-clockangle
Version: 1.0.0
Summary: A Python library to calculate the angle between the two hands of a clock.
Author: Niral Bhatt
Author-email: niralbhattdev@gmail.com
License: MIT
Classifier: Programming Language :: Python :: 3
Classifier: License :: OSI Approved :: MIT License
Classifier: Operating System :: OS Independent
Requires-Python: >=3.6
License-File: LICENSE
